<Ui xmlns="http://www.blizzard.com/wow/ui/">
  <Button name="Atr_Col_Heading_Template" virtual="true">
    <ButtonText name="$parentText">
      <Anchors>
        <Anchor point="LEFT">
          <Offset><AbsDimension x="8" y="0"/></Offset>
        </Anchor>
      </Anchors>
    </ButtonText>
    <NormalFont style="GameFontHighlightSmall"/>
    <NormalTexture name="$parentArrow" file="Interface\Buttons\UI-SortArrow">
      <Size><AbsDimension x="9" y="8"/></Size>
      <Anchors>
        <Anchor point="LEFT" relativeTo="$parentText" relativePoint="RIGHT">
          <Offset><AbsDimension x="3" y="-1"/></Offset>
        </Anchor>
      </Anchors>
      <TexCoords left="0" right="0.5625" top="0" bottom="1.0"/>
    </NormalTexture>
    <HighlightTexture file="Interface\PaperDollInfoFrame\UI-Character-Tab-Highlight" alphaMode="ADD">
      <Size><AbsDimension x="5" y="24"/></Size>
      <Anchors>
        <Anchor point="LEFT"><Offset><AbsDimension x="0" y="0"/></Offset></Anchor>
        <Anchor point="RIGHT"><Offset><AbsDimension x="4" y="0"/></Offset></Anchor>
      </Anchors>
    </HighlightTexture>
  </Button>
</Ui>